devsimpy/AIAdapter.py
devsimpy/AIPrompterDialog.py
devsimpy/AttributeEditor.py
devsimpy/CheckerGUI.py
devsimpy/Complexity.py
devsimpy/Components.py
devsimpy/ConnectDialog.py
devsimpy/ConnectionThread.py
devsimpy/Container.py
devsimpy/ControlNotebook.py
devsimpy/DSV.py
devsimpy/Decorators.py
devsimpy/DetachedFrame.py
devsimpy/DiagramConstantsDialog.py
devsimpy/DiagramNotebook.py
devsimpy/DirTreeCtrl.py
devsimpy/DragList.py
devsimpy/DropTarget.py
devsimpy/Editor.py
devsimpy/Event.py
devsimpy/ExperimentGenerator.py
devsimpy/FTPGUI.py
devsimpy/FindGUI.py
devsimpy/HtmlWindow.py
devsimpy/ImportLibrary.py
devsimpy/InteractionJSON.py
devsimpy/InteractionSocket.py
devsimpy/InteractionYAML.py
devsimpy/Join.py
devsimpy/LabelGUI.py
devsimpy/LibPanel.py
devsimpy/LibraryTree.py
devsimpy/Menu.py
devsimpy/NetManager.py
devsimpy/PlotGUI.py
devsimpy/PluginManager.py
devsimpy/PluginsGUI.py
devsimpy/PreferencesGUI.py
devsimpy/PrintOut.py
devsimpy/PriorityGUI.py
devsimpy/PropPanel.py
devsimpy/PropertiesGridCtrl.py
devsimpy/ReloadModule.py
devsimpy/Reporter.py
devsimpy/SimpleFrameEditor.py
devsimpy/SimulationGUI.py
devsimpy/SimulationNoGUI.py
devsimpy/SpreadSheet.py
devsimpy/StandaloneGUI.py
devsimpy/StandaloneNoGUI.py
devsimpy/Translation.py
devsimpy/Utilities.py
devsimpy/WizardGUI.py
devsimpy/XMLModule.py
devsimpy/YAMLExportGUI.py
devsimpy/ZipManager.py
devsimpy/__init__.py
devsimpy/config.py
devsimpy/devsimpy-nogui.py
devsimpy/devsimpy.py
devsimpy/maccabe.py
devsimpy/makePot.sh
devsimpy/reindent.py
devsimpy/searchTreeList.py
devsimpy/which.py
devsimpy/wxPyMail.py
devsimpy/AI/DEVS_Explanation.txt
devsimpy/DEVSKernel/__init__.py
devsimpy/DEVSKernel/PyDEVS/DEVS.py
devsimpy/DEVSKernel/PyDEVS/__init__.py
devsimpy/DEVSKernel/PyDEVS/simulator.py
devsimpy/DEVSKernel/PyDEVS/__pycache__/DEVS.cpython-313.pyc
devsimpy/DEVSKernel/PyDEVS/__pycache__/__init__.cpython-313.pyc
devsimpy/DEVSKernel/PyPDEVS/__init__.py
devsimpy/DEVSKernel/PyPDEVS/__pycache__/__init__.cpython-313.pyc
devsimpy-5.1.1.dist-info/METADATA
devsimpy-5.1.1.dist-info/WHEEL
devsimpy-5.1.1.dist-info/entry_points.txt
devsimpy-5.1.1.dist-info/top_level.txt
devsimpy-5.1.1.dist-info/RECORD
