Metadata-Version: 2.4
Name: devsimpy
Version: 5.1.1
Summary: Python-Based GUI for Discrete Event system Specification (DEVS) Simulation
Author-email: Laurent Capocchi <capocchi@univ-corse.fr>, Jean-Francois santucci <santuccig@univ-corse.fr>
Maintainer-email: Laurent Capocchi <capocchi@univ-corse.fr>
License: LICENSE
Project-URL: Homepage, https://capocchi-l.universita.corsica/article.php?id_site=58&id_menu=0&id_rub=663&id_cat=0&id_art=3257&lang=fr
Project-URL: Source Code, https://github.com/capocchi/DEVSimPy
Project-URL: Bug Tracker, https://github.com/capocchi/DEVSimPy/issues
Project-URL: Changelog, https://github.com/capocchi/DEVSimPy/blob/master/CHANGELOG.md
Keywords: Simulation,Modeling,Discrete Event,DEVS,GUI
Classifier: Development Status :: 5 - Production/Stable
Classifier: Intended Audience :: Developers
Classifier: Topic :: Software Development :: Build Tools
Classifier: Programming Language :: Python :: 3
Classifier: Programming Language :: Python :: 3.9
Classifier: Programming Language :: Python :: 3.10
Classifier: Programming Language :: Python :: 3.11
Classifier: Programming Language :: Python :: 3.12
Classifier: Programming Language :: Python :: 3.13
Classifier: Programming Language :: Python
Requires-Python: >=3.9
Requires-Dist: wxpython>=4.2.2
Requires-Dist: psutil
Requires-Dist: pyYAML
Requires-Dist: PyPubSub
Requires-Dist: ruamel.yaml
Requires-Dist: matplotlib
Requires-Dist: chart_studio
Requires-Dist: setuptools
Requires-Dist: pusher
Requires-Dist: ollama
Requires-Dist: openai
Requires-Dist: plotly
Requires-Dist: pyzo
Requires-Dist: pyro4
Requires-Dist: whichpy
Requires-Dist: requests
Requires-Dist: pluginmanager
Requires-Dist: numpy
Requires-Dist: pydot
Requires-Dist: networkx
Requires-Dist: lxml
Provides-Extra: gui
Requires-Dist: spyder; extra == "gui"
